helpmedosa/__init__.py
helpmedosa/helpmedosa.py
helpmedosa-0.3.0.dist-info/AUTHORS.rst
helpmedosa-0.3.0.dist-info/LICENSE
helpmedosa-0.3.0.dist-info/METADATA
helpmedosa-0.3.0.dist-info/WHEEL
helpmedosa-0.3.0.dist-info/top_level.txt
helpmedosa-0.3.0.dist-info/RECORD
