Metadata-Version: 2.1
Name: helpmedosa
Version: 0.3.0
Summary: Python Boilerplate contains all the boilerplate you need to create a Python package.
Home-page: 
Author: lilgoku
Author-email: lilgoku <lilgoku70@gmail.com>
Maintainer-email: lilgoku <lilgoku70@gmail.com>
License: MIT license
Project-URL: bugs, https://github.com/audreyr/helpmedosa/issues
Project-URL: changelog, https://github.com/audreyr/helpmedosa/blob/master/changelog.md
Project-URL: homepage, https://github.com/audreyr/helpmedosa
License-File: LICENSE
License-File: AUTHORS.rst
Provides-Extra: dev
Requires-Dist: coverage; extra == "dev"
Requires-Dist: mypy; extra == "dev"
Requires-Dist: pytest; extra == "dev"
Requires-Dist: ruff; extra == "dev"
